{
  "step_name": "Day 8-9: Master Configuration & Universal Pipeline - COMPLETED",
  "completed_at": "2025-05-31T03:11:23.182201",
  "files_created": [
    "src/colab/vietforex_api_enhanced.py",
    "src/colab/regime_detector.py",
    "src/colab/anti_leakage_validator.py",
    "src/colab/universal_data_pipeline.py",
    "src/colab/advanced_feature_engineer.py"
  ],
  "achievements": [
    "Enhanced API Client với master configuration system",
    "Market Regime Detection cho 4 regime types",
    "Anti-Leakage Validation framework",
    "Universal Data Pipeline với regime awareness",
    "Advanced Feature Engineering với 100+ features",
    "Template scalability validated cho EURUSD & GBPUSD",
    "Real-time API integration successful",
    "Comprehensive testing framework",
    "Performance optimization completed",
    "Ready cho Day 10 EURUSD historical data processing"
  ],
  "issues_encountered": "None - All systems operational and tested",
  "status": "completed"
}